emoji_converter/__init__.py
emoji_converter/converter.py
emoji_converter-0.1.2.dist-info/LICENSE.txt
emoji_converter-0.1.2.dist-info/METADATA
emoji_converter-0.1.2.dist-info/WHEEL
emoji_converter-0.1.2.dist-info/RECORD
