Metadata-Version: 2.1
Name: emoji-converter
Version: 0.1.2
Summary: A Python package for converting text to emoji and emoji to text.
Home-page: https://github.com/lemanh99/emoji-converter
License: MIT
Keywords: emoji,emoji converter,text to emoji,emoji to text
Author: Le Xuan Manh
Author-email: lexuanmanh101199@gmail.com
Requires-Python: >=3.6,<4.0
Classifier: License :: OSI Approved :: MIT License
Classifier: Programming Language :: Python :: 3
Classifier: Programming Language :: Python :: 3.6
Classifier: Programming Language :: Python :: 3.7
Classifier: Programming Language :: Python :: 3.8
Classifier: Programming Language :: Python :: 3.9
Classifier: Programming Language :: Python :: 3.10
Classifier: Programming Language :: Python :: 3.11
Requires-Dist: emoji (>=2.5.1,<3.0.0)
Project-URL: Repository, https://github.com/lemanh99/emoji-converter
